operation_profile_lib/__init__.py
operation_profile_lib/_modidx.py
operation_profile_lib/operation_profile_pb2.py
operation_profile_lib/operation_profile_structure.py
operation_profile_lib-0.1.12.dist-info/LICENSE
operation_profile_lib-0.1.12.dist-info/METADATA
operation_profile_lib-0.1.12.dist-info/WHEEL
operation_profile_lib-0.1.12.dist-info/entry_points.txt
operation_profile_lib-0.1.12.dist-info/top_level.txt
operation_profile_lib-0.1.12.dist-info/RECORD
